hello/__init__.py
hello/oissu.py
pypi_helloworld-0.1.dist-info/METADATA
pypi_helloworld-0.1.dist-info/RECORD
pypi_helloworld-0.1.dist-info/WHEEL
pypi_helloworld-0.1.dist-info/top_level.txt
